focosql/__init__.py
focosql/connection.py
focosql/queries.py
focosql-1.0.dist-info/METADATA
focosql-1.0.dist-info/WHEEL
focosql-1.0.dist-info/top_level.txt
focosql-1.0.dist-info/RECORD
